LICENSE
MANIFEST.in
README.md
setup.cfg
setup.py
goprohero/GoProHero.py
goprohero/__init__.py
goprohero.egg-info/PKG-INFO
goprohero.egg-info/SOURCES.txt
goprohero.egg-info/dependency_links.txt
goprohero.egg-info/not-zip-safe
goprohero.egg-info/requires.txt
goprohero.egg-info/top_level.txt
scripts/goproctl