Metadata-Version: 1.0
Name: goprohero
Version: 0.2.6
Summary: A Python library for controlling GoPro cameras over http.
Home-page: https://github.com/joshvillbrandt/gopro
Author: Josh Villbrandt
Author-email: josh@javconcepts.com
License: Apache License
